boto_model_py/__init__.py
boto_model_py/cli.py
boto_model_py/consts_source_code.py
boto_model_py/enum_writer.py
boto_model_py/json_processing.py
boto_model_py/output_file.py
boto_model_py/run.py
boto_model_py/source_code_editor.py
boto_model_py/temporary_file.py
boto_model_py/ast_processor/__init__.py
boto_model_py/ast_processor/consts_source_code.py
boto_model_py/ast_processor/converter.py
boto_model_py/ast_processor/field_type.py
boto_model_py/ast_processor/imports_handler.py
boto_model_py/preprocessor/__init__.py
boto_model_py/preprocessor/consts.py
boto_model_py/preprocessor/models.py
boto_model_py/preprocessor/preprocessing.py
boto_model_py-0.1.2.dist-info/LICENSE
boto_model_py-0.1.2.dist-info/METADATA
boto_model_py-0.1.2.dist-info/WHEEL
boto_model_py-0.1.2.dist-info/entry_points.txt
boto_model_py-0.1.2.dist-info/top_level.txt
boto_model_py-0.1.2.dist-info/RECORD
