Metadata-Version: 2.1
Name: boto-model-py
Version: 0.1.2
Summary: A code generation library that converts AWS boto3 responses into a Python module with fully hierarchical Python data classes
Author-email: Ori Poria <oriporia@gmail.com>
License: MIT
Classifier: Programming Language :: Python :: 3
Classifier: Operating System :: OS Independent
Requires-Python: >=3.9
License-File: LICENSE
Requires-Dist: pydantic <3
Requires-Dist: astor ==0.8.1
Requires-Dist: datamodel-code-generator ==0.25.7
